anomalearn/__init__.py
anomalearn/abc.py
anomalearn/algorithms/__init__.py
anomalearn/algorithms/algo_functions.py
anomalearn/algorithms/BaseModel.py
anomalearn/algorithms/IBoundaryClassifier.py
anomalearn/algorithms/IClassifier.py
anomalearn/algorithms/ICluster.py
anomalearn/algorithms/ICopyable.py
anomalearn/algorithms/IMultipleParametric.py
anomalearn/algorithms/IParametric.py
anomalearn/algorithms/IPredictor.py
anomalearn/algorithms/IProbabilisticClassifier.py
anomalearn/algorithms/IRegressor.py
anomalearn/algorithms/ISavable.py
anomalearn/algorithms/IShapeChanger.py
anomalearn/algorithms/ITransformer.py
anomalearn/algorithms/models/__init__.py
anomalearn/algorithms/models/IAnomalyScorer.py
anomalearn/algorithms/models/machine_learning/__init__.py
anomalearn/algorithms/models/machine_learning/IsolationForest.py
anomalearn/algorithms/models/neural/__init__.py
anomalearn/algorithms/models/statistical/__init__.py
anomalearn/algorithms/pipelines/__init__.py
anomalearn/algorithms/pipelines/AbstractPipelineBaseLayer.py
anomalearn/algorithms/pipelines/AbstractPipelineSavableLayer.py
anomalearn/algorithms/pipelines/IPipeline.py
anomalearn/algorithms/pipelines/IPipelineLayer.py
anomalearn/algorithms/pipelines/Pipeline.py
anomalearn/algorithms/postprocessing/__init__.py
anomalearn/algorithms/postprocessing/BuilderErrorVectorsAbsDifference.py
anomalearn/algorithms/postprocessing/BuilderErrorVectorsDifference.py
anomalearn/algorithms/postprocessing/BuilderErrorVectorsNorm.py
anomalearn/algorithms/postprocessing/BuilderVectorsSlidingWindow.py
anomalearn/algorithms/postprocessing/ScorerGaussian.py
anomalearn/algorithms/postprocessing/ScorerMahalanobis.py
anomalearn/algorithms/postprocessing/ThresholdMaxOnNormal.py
anomalearn/algorithms/preprocessing/__init__.py
anomalearn/algorithms/preprocessing/SlidingWindowForecast.py
anomalearn/algorithms/preprocessing/SlidingWindowReconstruct.py
anomalearn/algorithms/SavableModel.py
anomalearn/algorithms/transformers/__init__.py
anomalearn-0.0.2.dist-info/LICENSE
anomalearn-0.0.2.dist-info/METADATA
anomalearn-0.0.2.dist-info/WHEEL
anomalearn-0.0.2.dist-info/RECORD
