Metadata-Version: 2.1
Name: anomalearn
Version: 0.0.2
Summary: A modular and extensible end-to-end library for time series anomaly detection
Home-page: https://marcopetri98.github.io/anomalearn/index.html
License: European Union Public Licence 1.2 (EUPL 1.2)
Keywords: time series,anomaly detection,machine learning,development
Author: Marco Petri
Author-email: marco.petri@mail.polimi.it
Requires-Python: >=3.10
Classifier: Development Status :: 2 - Pre-Alpha
Classifier: Intended Audience :: Developers
Classifier: Intended Audience :: Science/Research
Classifier: License :: OSI Approved :: European Union Public Licence 1.2 (EUPL 1.2)
Classifier: License :: Other/Proprietary License
Classifier: Operating System :: OS Independent
Classifier: Programming Language :: Python :: 3
Classifier: Programming Language :: Python :: 3.10
Classifier: Programming Language :: Python :: 3.11
Classifier: Programming Language :: Python :: 3.10
Classifier: Programming Language :: Python :: 3.11
Classifier: Topic :: Scientific/Engineering :: Artificial Intelligence
Classifier: Topic :: Software Development :: Libraries :: Python Modules
Classifier: Typing :: Typed
Requires-Dist: matplotlib (>=3.5.1)
Requires-Dist: numba (>=0.56.4)
Requires-Dist: numpy (>=1.21.5)
Requires-Dist: pandas (>=1.4.1,<2.0.0)
Requires-Dist: scikit-learn (>=1.0.2)
Requires-Dist: scikit-optimize (>=0.9.0)
Requires-Dist: scipy (>=1.7.3)
Requires-Dist: statsmodels (>=0.13.0)
Project-URL: Documentation, https://marcopetri98.github.io/anomalearn/index.html
Project-URL: Repository, https://github.com/marcopetri98/anomalearn
